README.md
setup.py
lineage_keeper/__init__.py
lineage_keeper/housekeep.py
lineage_keeper/listener.py
lineage_keeper/viewer.py
lineage_keeper.egg-info/PKG-INFO
lineage_keeper.egg-info/SOURCES.txt
lineage_keeper.egg-info/dependency_links.txt
lineage_keeper.egg-info/requires.txt
lineage_keeper.egg-info/top_level.txt