Metadata-Version: 2.1
Name: lineage-keeper
Version: 0.2
Summary: A lightweight lineage tool based on Spark and Delta Lake
Home-page: https://github.com/otacilio-psf/lineage-keeper
Author: Otacilio Filho
Author-email: otaciliopedro@gmail.com
License: UNKNOWN
Platform: UNKNOWN
Classifier: Programming Language :: Python :: 3
Classifier: License :: OSI Approved :: MIT License
Classifier: Operating System :: OS Independent
